README.rst
setup.cfg
setup.py
TurboGears2.egg-info/PKG-INFO
TurboGears2.egg-info/SOURCES.txt
TurboGears2.egg-info/dependency_links.txt
TurboGears2.egg-info/entry_points.txt
TurboGears2.egg-info/not-zip-safe
TurboGears2.egg-info/pbr.json
TurboGears2.egg-info/requires.txt
TurboGears2.egg-info/top_level.txt
tests/__init__.py
tests/base.py
tests/test_balanced_session.py
tests/test_caching.py
tests/test_config_milestones.py
tests/test_configuration.py
tests/test_configuration_dictionary.py
tests/test_configuration_util.py
tests/test_controllers.py
tests/test_converters.py
tests/test_errorware.py
tests/test_fastform.py
tests/test_generic_json.py
tests/test_hooks.py
tests/test_i18n.py
tests/test_jsonify.py
tests/test_jsonify_sqlalchemy.py
tests/test_middlewares.py
tests/test_predicates.py
tests/test_render.py
tests/test_rest_controller_dispatch.py
tests/test_statics.py
tests/test_tg_controller_dispatch.py
tests/test_util.py
tests/test_validation.py
tests/fixtures/__init__.py
tests/fixtures/model.py
tests/test_stack/__init__.py
tests/test_stack/baseutils.py
tests/test_stack/test_authz.py
tests/test_stack/test_registry.py
tests/test_stack/test_request_local.py
tests/test_stack/config/__init__.py
tests/test_stack/config/test_config.py
tests/test_stack/config/controllers/__init__.py
tests/test_stack/config/controllers/root.py
tests/test_stack/dispatch/__init__.py
tests/test_stack/dispatch/test_config.py
tests/test_stack/dispatch/test_decorated_controller.py
tests/test_stack/dispatch/test_url_dispatch.py
tests/test_stack/dispatch/controllers/__init__.py
tests/test_stack/dispatch/controllers/root.py
tests/test_stack/fixture/__init__.py
tests/test_stack/lib/__init__.py
tests/test_stack/lib/base.py
tests/test_stack/lib/helpers.py
tests/test_stack/lib/templatetools/__init__.py
tests/test_stack/lib/templatetools/jinja_filters.py
tests/test_stack/rendering/__init__.py
tests/test_stack/rendering/test_decorators.py
tests/test_stack/rendering/test_dotted_rendering.py
tests/test_stack/rendering/test_pagination.py
tests/test_stack/rendering/test_rendering.py
tests/test_stack/rendering/test_toscawidgets.py
tests/test_stack/rendering/controllers/__init__.py
tests/test_stack/rendering/controllers/root.py
tests/test_stack/rendering/templates/__init__.py
