Metadata-Version: 1.1
Name: TurboGears2
Version: 2.3.8
Summary: Next generation TurboGears
Home-page: http://www.turbogears.org/
Author: Mark Ramm, Christopher Perkins, Jonathan LaCour, Rick Copland, Alberto Valverde, Michael Pedersen, Alessandro Molina, and the TurboGears community
Author-email: mark.ramm@gmail.com, alberto@toscat.net, m.pedersen@icelus.org, amol@turbogears.org
License: MIT
Keywords: turbogears
Platform: UNKNOWN
Classifier: Intended Audience :: Developers
Classifier: Environment :: Web Environment
Classifier: Programming Language :: Python :: 3
Classifier: Programming Language :: Python
Classifier: Topic :: Internet :: WWW/HTTP
Classifier: Topic :: Internet :: WWW/HTTP :: WSGI
